napping/__init__.py
napping/__main__.py
napping/_napping_application.py
napping/_napping_exception.py
napping/_napping_navigator.py
napping/_version.py
napping/qt/__init__.py
napping/qt/_file_line_edit.py
napping/qt/_napping_dialog.py
napping/qt/_napping_viewer.py
napping/qt/_napping_widget.py
napping-0.2.4.dist-info/LICENSE
napping-0.2.4.dist-info/METADATA
napping-0.2.4.dist-info/WHEEL
napping-0.2.4.dist-info/entry_points.txt
napping-0.2.4.dist-info/top_level.txt
napping-0.2.4.dist-info/RECORD
