Metadata-Version: 2.1
Name: napping
Version: 0.2.4
Summary: Control point mapping and coordination transformation using napari
Home-page: https://github.com/BodenmillerGroup/napping
Author: Jonas Windhager
Author-email: jonas.windhager@uzh.ch
License: MIT
Project-URL: Bug Tracker, https://github.com/BodenmillerGroup/napping/issues
Project-URL: Documentation, https://github.com/BodenmillerGroup/napping/#README.md
Project-URL: Source Code, https://github.com/BodenmillerGroup/napping
Project-URL: User Support, https://github.com/BodenmillerGroup/napping/issues
Classifier: Development Status :: 4 - Beta
Classifier: Intended Audience :: Science/Research
Classifier: Framework :: napari
Classifier: Topic :: Scientific/Engineering :: Bio-Informatics
Classifier: Topic :: Scientific/Engineering :: Image Processing
Classifier: Programming Language :: Python
Classifier: Programming Language :: Python :: 3
Classifier: Programming Language :: Python :: 3.8
Classifier: Programming Language :: Python :: 3.9
Classifier: Operating System :: OS Independent
Classifier: License :: OSI Approved :: MIT License
Requires-Python: >=3.8
License-File: LICENSE
Requires-Dist: imagecodecs
Requires-Dist: imageio
Requires-Dist: napari[all] (>=0.4.16)
Requires-Dist: numpy
Requires-Dist: pandas
Requires-Dist: qtpy
Requires-Dist: scikit-image
